[{"id":"062c3335-08ef-4d16-b781-2a7e0b5088f7","createdAt":1740101876.206260800,"updatedAt":1740101876.206260800,"name":"Second 채널","description":"업데이트된 채널 설명","creatorId":"f66c35bb-18b5-43e4-9208-006090969a2a","members":[],"public":true,"private":false},{"id":"8c597a9b-16d1-4ca3-a4aa-d79618591517","createdAt":1740103962.759702200,"updatedAt":1740103962.759702200,"name":"Second 채널","description":"업데이트된 채널 설명","creatorId":"aef53823-90d6-4154-8723-78dd17dfb964","members":[],"public":true,"private":false},{"id":"3e057ab9-d542-49f0-aa13-ead8c2ca713d","createdAt":1740104343.568108800,"updatedAt":1740104343.568108800,"name":"Second 채널","description":"업데이트된 채널 설명","creatorId":"d1ffc9da-cbdc-4ae6-8beb-4558fc7b2dc3","members":[],"public":true,"private":false}]